fbc_curation/__init__.py
fbc_curation/compare.py
fbc_curation/examples.py
fbc_curation/frog.py
fbc_curation/runfrog.py
fbc_curation/schema.py
fbc_curation/worker.py
fbc_curation/cameo/__init__.py
fbc_curation/cameo/flux_analysis/__init__.py
fbc_curation/cameo/flux_analysis/analysis.py
fbc_curation/cameo/flux_analysis/simulation.py
fbc_curation/curator/__init__.py
fbc_curation/curator/cameo_curator.py
fbc_curation/curator/cobrapy_curator.py
fbc_curation/curator/curator.py
fbc_curation/resources/examples/frogs/e_coli_core_FROG.omex
fbc_curation/resources/examples/frogs/e_coli_core_no_genes_FROG.omex
fbc_curation/resources/examples/frogs/iCGB21FR_FROG.omex
fbc_curation/resources/examples/frogs/iJR904_FROG.omex
fbc_curation/resources/examples/models/LICENSE
fbc_curation/resources/examples/models/e_coli_core.omex
fbc_curation/resources/examples/models/e_coli_core.xml
fbc_curation/resources/examples/models/e_coli_core_FROG.omex
fbc_curation/resources/examples/models/e_coli_core_no_genes.xml
fbc_curation/resources/examples/models/example_docs.py
fbc_curation/resources/examples/models/iCGB21FR.omex
fbc_curation/resources/examples/models/iJR904.omex
fbc_curation/resources/examples/models/iJR904.xml
fbc_curation/resources/schema/frog-schema-version-1.json
fbc_curation/resources/scripts/runfrogs.py
fbc_curation-0.3.2.dist-info/METADATA
fbc_curation-0.3.2.dist-info/WHEEL
fbc_curation-0.3.2.dist-info/entry_points.txt
fbc_curation-0.3.2.dist-info/licenses/LICENSE
fbc_curation-0.3.2.dist-info/RECORD
