Metadata-Version: 2.4
Name: fbc_curation
Version: 0.3.2
Summary: FBC reference files for SBML model curation.
Author-email: Matthias König <konigmatt@googlemail.com>
Maintainer-email: Matthias König <konigmatt@googlemail.com>
License-File: LICENSE
Keywords: COMBINE,SBML,annotation,archive,fbc,metadata,modeling,reproducibility,standardization
Classifier: Development Status :: 4 - Beta
Classifier: Intended Audience :: Science/Research
Classifier: License :: OSI Approved :: MIT License
Classifier: Operating System :: OS Independent
Classifier: Programming Language :: Python :: 3.11
Classifier: Programming Language :: Python :: 3.12
Classifier: Programming Language :: Python :: 3.13
Classifier: Programming Language :: Python :: Implementation :: CPython
Classifier: Topic :: Scientific/Engineering
Classifier: Topic :: Scientific/Engineering :: Bio-Informatics
Requires-Python: >=3.11
Requires-Dist: cobra>=0.29.1
Requires-Dist: numpy>=2.3.3
Requires-Dist: optlang
Requires-Dist: orjson>=3.11.3
Requires-Dist: pandas>=2.3.2
Requires-Dist: pydantic>=2.11.9
Requires-Dist: pymetadata>=0.5.4
Requires-Dist: rich>=14.1.0
Requires-Dist: sympy
Provides-Extra: dev
Requires-Dist: bump-my-version>=1.2.3; extra == 'dev'
Requires-Dist: mypy>=1.18.2; extra == 'dev'
Requires-Dist: pre-commit>=4.3.0; extra == 'dev'
Requires-Dist: pytest-cov>=7.0.0; extra == 'dev'
Requires-Dist: pytest>=8.4.2; extra == 'dev'
Requires-Dist: ruff>=0.13.1; extra == 'dev'
Requires-Dist: tox>=4.30.2; extra == 'dev'
Provides-Extra: docs
Requires-Dist: mkdocs; extra == 'docs'
Requires-Dist: mkdocs-jupyter; extra == 'docs'
Requires-Dist: mkdocs-material; extra == 'docs'
Requires-Dist: mkdocstrings-python; extra == 'docs'
